Metadata-Version: 2.1
Name: tebbytools
Version: 0.3.5
Summary: A set of simple tools for language learning.
Home-page: https://github.com/tebby24/tebbytools
Author: Teddy Gonyea
Author-email: enterted@gmail.com
Keywords: language learning
